[
  {
    "time": "2026-05-29 09:15:00",
    "direction": "SELL",
    "open": 4528.992,
    "high": 4529.706,
    "low": 4526.808,
    "close": 4527.839,
    "volume": 905,
    "candle_data": {
      "body": "11.53 pips",
      "ekor_atas": "7.14 pips",
      "ekor_bawah": "10.31 pips"
    }
  },
  {
    "time": "2026-05-29 09:20:00",
    "direction": "SELL",
    "open": 4527.764,
    "high": 4528.25,
    "low": 4522.088,
    "close": 4522.793,
    "volume": 699,
    "candle_data": {
      "body": "49.71 pips",
      "ekor_atas": "4.86 pips",
      "ekor_bawah": "7.05 pips"
    }
  },
  {
    "time": "2026-05-29 09:25:00",
    "direction": "BUY",
    "open": 4522.557,
    "high": 4532.327,
    "low": 4522.457,
    "close": 4528.723,
    "volume": 898,
    "candle_data": {
      "body": "61.66 pips",
      "ekor_atas": "36.04 pips",
      "ekor_bawah": "1.0 pips"
    }
  },
  {
    "time": "2026-05-29 09:30:00",
    "direction": "SELL",
    "open": 4528.952,
    "high": 4530.799,
    "low": 4524.682,
    "close": 4528.494,
    "volume": 1126,
    "candle_data": {
      "body": "4.58 pips",
      "ekor_atas": "18.47 pips",
      "ekor_bawah": "38.12 pips"
    }
  },
  {
    "time": "2026-05-29 09:35:00",
    "direction": "BUY",
    "open": 4528.439,
    "high": 4530.411,
    "low": 4526.628,
    "close": 4528.637,
    "volume": 736,
    "candle_data": {
      "body": "1.98 pips",
      "ekor_atas": "17.74 pips",
      "ekor_bawah": "18.11 pips"
    }
  },
  {
    "time": "2026-05-29 09:40:00",
    "direction": "BUY",
    "open": 4528.936,
    "high": 4532.657,
    "low": 4527.962,
    "close": 4532.225,
    "volume": 653,
    "candle_data": {
      "body": "32.89 pips",
      "ekor_atas": "4.32 pips",
      "ekor_bawah": "9.74 pips"
    }
  },
  {
    "time": "2026-05-29 09:45:00",
    "direction": "BUY",
    "open": 4532.29,
    "high": 4537.845,
    "low": 4531.811,
    "close": 4536.989,
    "volume": 1098,
    "candle_data": {
      "body": "46.99 pips",
      "ekor_atas": "8.56 pips",
      "ekor_bawah": "4.79 pips"
    }
  },
  {
    "time": "2026-05-29 09:50:00",
    "direction": "SELL",
    "open": 4537.057,
    "high": 4539.763,
    "low": 4531.265,
    "close": 4532.766,
    "volume": 968,
    "candle_data": {
      "body": "42.91 pips",
      "ekor_atas": "27.06 pips",
      "ekor_bawah": "15.01 pips"
    }
  },
  {
    "time": "2026-05-29 09:55:00",
    "direction": "SELL",
    "open": 4532.706,
    "high": 4533.39,
    "low": 4529.648,
    "close": 4531.207,
    "volume": 668,
    "candle_data": {
      "body": "14.99 pips",
      "ekor_atas": "6.84 pips",
      "ekor_bawah": "15.59 pips"
    }
  },
  {
    "time": "2026-05-29 10:00:00",
    "direction": "SELL",
    "open": 4531.211,
    "high": 4531.211,
    "low": 4525.488,
    "close": 4526.111,
    "volume": 542,
    "candle_data": {
      "body": "51.0 pips",
      "ekor_atas": "0.0 pips",
      "ekor_bawah": "6.23 pips"
    }
  },
  {
    "time": "2026-05-29 10:05:00",
    "direction": "BUY",
    "open": 4526.135,
    "high": 4528.754,
    "low": 4526.025,
    "close": 4526.264,
    "volume": 629,
    "candle_data": {
      "body": "1.29 pips",
      "ekor_atas": "24.9 pips",
      "ekor_bawah": "1.1 pips"
    }
  },
  {
    "time": "2026-05-29 10:10:00",
    "direction": "BUY",
    "open": 4526.567,
    "high": 4528.604,
    "low": 4525.736,
    "close": 4528.363,
    "volume": 749,
    "candle_data": {
      "body": "17.96 pips",
      "ekor_atas": "2.41 pips",
      "ekor_bawah": "8.31 pips"
    }
  },
  {
    "time": "2026-05-29 10:15:00",
    "direction": "SELL",
    "open": 4528.298,
    "high": 4530.285,
    "low": 4525.595,
    "close": 4526.587,
    "volume": 719,
    "candle_data": {
      "body": "17.11 pips",
      "ekor_atas": "19.87 pips",
      "ekor_bawah": "9.92 pips"
    }
  },
  {
    "time": "2026-05-29 10:20:00",
    "direction": "BUY",
    "open": 4526.918,
    "high": 4527.877,
    "low": 4525.969,
    "close": 4527.49,
    "volume": 597,
    "candle_data": {
      "body": "5.72 pips",
      "ekor_atas": "3.87 pips",
      "ekor_bawah": "9.49 pips"
    }
  },
  {
    "time": "2026-05-29 10:25:00",
    "direction": "BUY",
    "open": 4527.413,
    "high": 4531.077,
    "low": 4527.288,
    "close": 4530.556,
    "volume": 602,
    "candle_data": {
      "body": "31.43 pips",
      "ekor_atas": "5.21 pips",
      "ekor_bawah": "1.25 pips"
    }
  },
  {
    "time": "2026-05-29 10:30:00",
    "direction": "BUY",
    "open": 4530.426,
    "high": 4539.175,
    "low": 4530.155,
    "close": 4538.669,
    "volume": 953,
    "candle_data": {
      "body": "82.43 pips",
      "ekor_atas": "5.06 pips",
      "ekor_bawah": "2.71 pips"
    }
  },
  {
    "time": "2026-05-29 10:35:00",
    "direction": "BUY",
    "open": 4538.73,
    "high": 4543.432,
    "low": 4538.063,
    "close": 4541.46,
    "volume": 982,
    "candle_data": {
      "body": "27.3 pips",
      "ekor_atas": "19.72 pips",
      "ekor_bawah": "6.67 pips"
    }
  },
  {
    "time": "2026-05-29 10:40:00",
    "direction": "SELL",
    "open": 4541.555,
    "high": 4542.175,
    "low": 4536.192,
    "close": 4537.887,
    "volume": 780,
    "candle_data": {
      "body": "36.68 pips",
      "ekor_atas": "6.2 pips",
      "ekor_bawah": "16.95 pips"
    }
  },
  {
    "time": "2026-05-29 10:45:00",
    "direction": "SELL",
    "open": 4537.927,
    "high": 4541.039,
    "low": 4536.158,
    "close": 4537.259,
    "volume": 848,
    "candle_data": {
      "body": "6.68 pips",
      "ekor_atas": "31.12 pips",
      "ekor_bawah": "11.01 pips"
    }
  },
  {
    "time": "2026-05-29 10:50:00",
    "direction": "SELL",
    "open": 4537.323,
    "high": 4539.109,
    "low": 4536.798,
    "close": 4536.798,
    "volume": 612,
    "candle_data": {
      "body": "5.25 pips",
      "ekor_atas": "17.86 pips",
      "ekor_bawah": "0.0 pips"
    }
  },
  {
    "time": "2026-05-29 10:55:00",
    "direction": "BUY",
    "open": 4536.863,
    "high": 4538.68,
    "low": 4535.166,
    "close": 4538.388,
    "volume": 750,
    "candle_data": {
      "body": "15.25 pips",
      "ekor_atas": "2.92 pips",
      "ekor_bawah": "16.97 pips"
    }
  },
  {
    "time": "2026-05-29 11:00:00",
    "direction": "SELL",
    "open": 4538.614,
    "high": 4540.538,
    "low": 4535.442,
    "close": 4535.944,
    "volume": 912,
    "candle_data": {
      "body": "26.7 pips",
      "ekor_atas": "19.24 pips",
      "ekor_bawah": "5.02 pips"
    }
  },
  {
    "time": "2026-05-29 11:05:00",
    "direction": "SELL",
    "open": 4535.929,
    "high": 4537.048,
    "low": 4532.042,
    "close": 4532.634,
    "volume": 700,
    "candle_data": {
      "body": "32.95 pips",
      "ekor_atas": "11.19 pips",
      "ekor_bawah": "5.92 pips"
    }
  },
  {
    "time": "2026-05-29 11:10:00",
    "direction": "BUY",
    "open": 4532.281,
    "high": 4533.419,
    "low": 4530.735,
    "close": 4532.423,
    "volume": 802,
    "candle_data": {
      "body": "1.42 pips",
      "ekor_atas": "9.96 pips",
      "ekor_bawah": "15.46 pips"
    }
  },
  {
    "time": "2026-05-29 11:15:00",
    "direction": "SELL",
    "open": 4532.159,
    "high": 4532.643,
    "low": 4529.235,
    "close": 4531.443,
    "volume": 772,
    "candle_data": {
      "body": "7.16 pips",
      "ekor_atas": "4.84 pips",
      "ekor_bawah": "22.08 pips"
    }
  },
  {
    "time": "2026-05-29 11:20:00",
    "direction": "SELL",
    "open": 4531.681,
    "high": 4534.412,
    "low": 4530.277,
    "close": 4531.364,
    "volume": 802,
    "candle_data": {
      "body": "3.17 pips",
      "ekor_atas": "27.31 pips",
      "ekor_bawah": "10.87 pips"
    }
  },
  {
    "time": "2026-05-29 11:25:00",
    "direction": "SELL",
    "open": 4531.42,
    "high": 4532.098,
    "low": 4526.924,
    "close": 4528.118,
    "volume": 786,
    "candle_data": {
      "body": "33.02 pips",
      "ekor_atas": "6.78 pips",
      "ekor_bawah": "11.94 pips"
    }
  },
  {
    "time": "2026-05-29 11:30:00",
    "direction": "SELL",
    "open": 4528.183,
    "high": 4528.625,
    "low": 4525.807,
    "close": 4527.213,
    "volume": 752,
    "candle_data": {
      "body": "9.7 pips",
      "ekor_atas": "4.42 pips",
      "ekor_bawah": "14.06 pips"
    }
  },
  {
    "time": "2026-05-29 11:35:00",
    "direction": "BUY",
    "open": 4527.168,
    "high": 4528.925,
    "low": 4526.535,
    "close": 4528.484,
    "volume": 660,
    "candle_data": {
      "body": "13.16 pips",
      "ekor_atas": "4.41 pips",
      "ekor_bawah": "6.33 pips"
    }
  },
  {
    "time": "2026-05-29 11:40:00",
    "direction": "BUY",
    "open": 4528.188,
    "high": 4531.323,
    "low": 4528.17,
    "close": 4530.939,
    "volume": 563,
    "candle_data": {
      "body": "27.51 pips",
      "ekor_atas": "3.84 pips",
      "ekor_bawah": "0.18 pips"
    }
  },
  {
    "time": "2026-05-29 11:45:00",
    "direction": "SELL",
    "open": 4530.959,
    "high": 4533.831,
    "low": 4529.041,
    "close": 4529.188,
    "volume": 587,
    "candle_data": {
      "body": "17.71 pips",
      "ekor_atas": "28.72 pips",
      "ekor_bawah": "1.47 pips"
    }
  },
  {
    "time": "2026-05-29 11:50:00",
    "direction": "BUY",
    "open": 4529.082,
    "high": 4535.289,
    "low": 4527.31,
    "close": 4533.809,
    "volume": 1618,
    "candle_data": {
      "body": "47.27 pips",
      "ekor_atas": "14.8 pips",
      "ekor_bawah": "17.72 pips"
    }
  },
  {
    "time": "2026-05-29 11:55:00",
    "direction": "BUY",
    "open": 4533.868,
    "high": 4538.939,
    "low": 4533.671,
    "close": 4538.213,
    "volume": 902,
    "candle_data": {
      "body": "43.45 pips",
      "ekor_atas": "7.26 pips",
      "ekor_bawah": "1.97 pips"
    }
  },
  {
    "time": "2026-05-29 12:00:00",
    "direction": "SELL",
    "open": 4538.278,
    "high": 4538.546,
    "low": 4528.13,
    "close": 4529.515,
    "volume": 777,
    "candle_data": {
      "body": "87.63 pips",
      "ekor_atas": "2.68 pips",
      "ekor_bawah": "13.85 pips"
    }
  },
  {
    "time": "2026-05-29 12:05:00",
    "direction": "BUY",
    "open": 4529.451,
    "high": 4530.522,
    "low": 4527.228,
    "close": 4530.294,
    "volume": 1042,
    "candle_data": {
      "body": "8.43 pips",
      "ekor_atas": "2.28 pips",
      "ekor_bawah": "22.23 pips"
    }
  },
  {
    "time": "2026-05-29 12:10:00",
    "direction": "SELL",
    "open": 4529.945,
    "high": 4532.075,
    "low": 4526.959,
    "close": 4528.471,
    "volume": 951,
    "candle_data": {
      "body": "14.74 pips",
      "ekor_atas": "21.3 pips",
      "ekor_bawah": "15.12 pips"
    }
  },
  {
    "time": "2026-05-29 12:15:00",
    "direction": "BUY",
    "open": 4528.409,
    "high": 4531.982,
    "low": 4527.458,
    "close": 4530.214,
    "volume": 754,
    "candle_data": {
      "body": "18.05 pips",
      "ekor_atas": "17.68 pips",
      "ekor_bawah": "9.51 pips"
    }
  },
  {
    "time": "2026-05-29 12:20:00",
    "direction": "SELL",
    "open": 4530.151,
    "high": 4530.151,
    "low": 4519.79,
    "close": 4523.624,
    "volume": 1469,
    "candle_data": {
      "body": "65.27 pips",
      "ekor_atas": "0.0 pips",
      "ekor_bawah": "38.34 pips"
    }
  },
  {
    "time": "2026-05-29 12:25:00",
    "direction": "SELL",
    "open": 4523.551,
    "high": 4524.658,
    "low": 4520.504,
    "close": 4522.226,
    "volume": 893,
    "candle_data": {
      "body": "13.25 pips",
      "ekor_atas": "11.07 pips",
      "ekor_bawah": "17.22 pips"
    }
  },
  {
    "time": "2026-05-29 12:30:00",
    "direction": "SELL",
    "open": 4522.173,
    "high": 4523.646,
    "low": 4514.911,
    "close": 4517.232,
    "volume": 1527,
    "candle_data": {
      "body": "49.41 pips",
      "ekor_atas": "14.73 pips",
      "ekor_bawah": "23.21 pips"
    }
  },
  {
    "time": "2026-05-29 12:35:00",
    "direction": "BUY",
    "open": 4517.173,
    "high": 4518.928,
    "low": 4515.266,
    "close": 4517.494,
    "volume": 1199,
    "candle_data": {
      "body": "3.21 pips",
      "ekor_atas": "14.34 pips",
      "ekor_bawah": "19.07 pips"
    }
  },
  {
    "time": "2026-05-29 12:40:00",
    "direction": "SELL",
    "open": 4517.436,
    "high": 4517.911,
    "low": 4512.718,
    "close": 4514.428,
    "volume": 1063,
    "candle_data": {
      "body": "30.08 pips",
      "ekor_atas": "4.75 pips",
      "ekor_bawah": "17.1 pips"
    }
  },
  {
    "time": "2026-05-29 12:45:00",
    "direction": "BUY",
    "open": 4514.366,
    "high": 4517.9,
    "low": 4512.523,
    "close": 4515.627,
    "volume": 1120,
    "candle_data": {
      "body": "12.61 pips",
      "ekor_atas": "22.73 pips",
      "ekor_bawah": "18.43 pips"
    }
  },
  {
    "time": "2026-05-29 12:50:00",
    "direction": "BUY",
    "open": 4515.682,
    "high": 4520.094,
    "low": 4514.384,
    "close": 4518.45,
    "volume": 1180,
    "candle_data": {
      "body": "27.68 pips",
      "ekor_atas": "16.44 pips",
      "ekor_bawah": "12.98 pips"
    }
  },
  {
    "time": "2026-05-29 12:55:00",
    "direction": "BUY",
    "open": 4518.688,
    "high": 4524.002,
    "low": 4516.565,
    "close": 4522.857,
    "volume": 1014,
    "candle_data": {
      "body": "41.69 pips",
      "ekor_atas": "11.45 pips",
      "ekor_bawah": "21.23 pips"
    }
  },
  {
    "time": "2026-05-29 13:00:00",
    "direction": "BUY",
    "open": 4522.915,
    "high": 4525.661,
    "low": 4516.766,
    "close": 4524.026,
    "volume": 2069,
    "candle_data": {
      "body": "11.11 pips",
      "ekor_atas": "16.35 pips",
      "ekor_bawah": "61.49 pips"
    }
  },
  {
    "time": "2026-05-29 13:05:00",
    "direction": "BUY",
    "open": 4524.085,
    "high": 4527.064,
    "low": 4515.043,
    "close": 4525.382,
    "volume": 1496,
    "candle_data": {
      "body": "12.97 pips",
      "ekor_atas": "16.82 pips",
      "ekor_bawah": "90.42 pips"
    }
  },
  {
    "time": "2026-05-29 13:10:00",
    "direction": "SELL",
    "open": 4525.386,
    "high": 4525.574,
    "low": 4520.691,
    "close": 4522.77,
    "volume": 1016,
    "candle_data": {
      "body": "26.16 pips",
      "ekor_atas": "1.88 pips",
      "ekor_bawah": "20.79 pips"
    }
  },
  {
    "time": "2026-05-29 13:15:00",
    "direction": "SELL",
    "open": 4522.826,
    "high": 4524.251,
    "low": 4521.282,
    "close": 4522.434,
    "volume": 1019,
    "candle_data": {
      "body": "3.92 pips",
      "ekor_atas": "14.25 pips",
      "ekor_bawah": "11.52 pips"
    }
  },
  {
    "time": "2026-05-29 13:20:00",
    "direction": "BUY",
    "open": 4522.379,
    "high": 4529.225,
    "low": 4522.379,
    "close": 4526.367,
    "volume": 1039,
    "candle_data": {
      "body": "39.88 pips",
      "ekor_atas": "28.58 pips",
      "ekor_bawah": "0.0 pips"
    }
  },
  {
    "time": "2026-05-29 13:25:00",
    "direction": "BUY",
    "open": 4526.428,
    "high": 4528.292,
    "low": 4525.362,
    "close": 4528.186,
    "volume": 1069,
    "candle_data": {
      "body": "17.58 pips",
      "ekor_atas": "1.06 pips",
      "ekor_bawah": "10.66 pips"
    }
  },
  {
    "time": "2026-05-29 13:30:00",
    "direction": "SELL",
    "open": 4527.998,
    "high": 4532.149,
    "low": 4524.978,
    "close": 4525.188,
    "volume": 2232,
    "candle_data": {
      "body": "28.1 pips",
      "ekor_atas": "41.51 pips",
      "ekor_bawah": "2.1 pips"
    }
  },
  {
    "time": "2026-05-29 13:35:00",
    "direction": "BUY",
    "open": 4525.004,
    "high": 4533.081,
    "low": 4522.452,
    "close": 4531.487,
    "volume": 2038,
    "candle_data": {
      "body": "64.83 pips",
      "ekor_atas": "15.94 pips",
      "ekor_bawah": "25.52 pips"
    }
  },
  {
    "time": "2026-05-29 13:40:00",
    "direction": "BUY",
    "open": 4531.423,
    "high": 4535.228,
    "low": 4530.27,
    "close": 4532.855,
    "volume": 1323,
    "candle_data": {
      "body": "14.32 pips",
      "ekor_atas": "23.73 pips",
      "ekor_bawah": "11.53 pips"
    }
  },
  {
    "time": "2026-05-29 13:45:00",
    "direction": "BUY",
    "open": 4532.8,
    "high": 4536.933,
    "low": 4529.519,
    "close": 4535.635,
    "volume": 1126,
    "candle_data": {
      "body": "28.35 pips",
      "ekor_atas": "12.98 pips",
      "ekor_bawah": "32.81 pips"
    }
  },
  {
    "time": "2026-05-29 13:50:00",
    "direction": "BUY",
    "open": 4535.698,
    "high": 4539.219,
    "low": 4531.983,
    "close": 4538.438,
    "volume": 1658,
    "candle_data": {
      "body": "27.4 pips",
      "ekor_atas": "7.81 pips",
      "ekor_bawah": "37.15 pips"
    }
  },
  {
    "time": "2026-05-29 13:55:00",
    "direction": "SELL",
    "open": 4538.362,
    "high": 4540.785,
    "low": 4535.12,
    "close": 4536.824,
    "volume": 1670,
    "candle_data": {
      "body": "15.38 pips",
      "ekor_atas": "24.23 pips",
      "ekor_bawah": "17.04 pips"
    }
  },
  {
    "time": "2026-05-29 14:00:00",
    "direction": "BUY",
    "open": 4536.702,
    "high": 4549.304,
    "low": 4535.057,
    "close": 4547.853,
    "volume": 2801,
    "candle_data": {
      "body": "111.51 pips",
      "ekor_atas": "14.51 pips",
      "ekor_bawah": "16.45 pips"
    }
  },
  {
    "time": "2026-05-29 14:05:00",
    "direction": "BUY",
    "open": 4547.912,
    "high": 4552.607,
    "low": 4546.103,
    "close": 4550.938,
    "volume": 2111,
    "candle_data": {
      "body": "30.26 pips",
      "ekor_atas": "16.69 pips",
      "ekor_bawah": "18.09 pips"
    }
  },
  {
    "time": "2026-05-29 14:10:00",
    "direction": "SELL",
    "open": 4550.867,
    "high": 4552.715,
    "low": 4543.844,
    "close": 4543.905,
    "volume": 1912,
    "candle_data": {
      "body": "69.62 pips",
      "ekor_atas": "18.48 pips",
      "ekor_bawah": "0.61 pips"
    }
  },
  {
    "time": "2026-05-29 14:15:00",
    "direction": "SELL",
    "open": 4543.964,
    "high": 4545.081,
    "low": 4537.888,
    "close": 4537.998,
    "volume": 1968,
    "candle_data": {
      "body": "59.66 pips",
      "ekor_atas": "11.17 pips",
      "ekor_bawah": "1.1 pips"
    }
  },
  {
    "time": "2026-05-29 14:20:00",
    "direction": "SELL",
    "open": 4537.941,
    "high": 4540.397,
    "low": 4530.81,
    "close": 4530.987,
    "volume": 1881,
    "candle_data": {
      "body": "69.54 pips",
      "ekor_atas": "24.56 pips",
      "ekor_bawah": "1.77 pips"
    }
  },
  {
    "time": "2026-05-29 14:25:00",
    "direction": "SELL",
    "open": 4531.045,
    "high": 4533.389,
    "low": 4526.068,
    "close": 4529.931,
    "volume": 2727,
    "candle_data": {
      "body": "11.14 pips",
      "ekor_atas": "23.44 pips",
      "ekor_bawah": "38.63 pips"
    }
  },
  {
    "time": "2026-05-29 14:30:00",
    "direction": "BUY",
    "open": 4529.548,
    "high": 4536.399,
    "low": 4525.135,
    "close": 4535.902,
    "volume": 2374,
    "candle_data": {
      "body": "63.54 pips",
      "ekor_atas": "4.97 pips",
      "ekor_bawah": "44.13 pips"
    }
  },
  {
    "time": "2026-05-29 14:35:00",
    "direction": "SELL",
    "open": 4535.98,
    "high": 4536.636,
    "low": 4530.719,
    "close": 4531.815,
    "volume": 1712,
    "candle_data": {
      "body": "41.65 pips",
      "ekor_atas": "6.56 pips",
      "ekor_bawah": "10.96 pips"
    }
  },
  {
    "time": "2026-05-29 14:40:00",
    "direction": "BUY",
    "open": 4531.755,
    "high": 4541.945,
    "low": 4531.755,
    "close": 4540.235,
    "volume": 2098,
    "candle_data": {
      "body": "84.8 pips",
      "ekor_atas": "17.1 pips",
      "ekor_bawah": "0.0 pips"
    }
  },
  {
    "time": "2026-05-29 14:45:00",
    "direction": "SELL",
    "open": 4540.475,
    "high": 4541.106,
    "low": 4536.505,
    "close": 4539.555,
    "volume": 1452,
    "candle_data": {
      "body": "9.2 pips",
      "ekor_atas": "6.31 pips",
      "ekor_bawah": "30.5 pips"
    }
  },
  {
    "time": "2026-05-29 14:50:00",
    "direction": "BUY",
    "open": 4539.778,
    "high": 4569.288,
    "low": 4539.649,
    "close": 4556.937,
    "volume": 5981,
    "candle_data": {
      "body": "171.59 pips",
      "ekor_atas": "123.51 pips",
      "ekor_bawah": "1.29 pips"
    }
  },
  {
    "time": "2026-05-29 14:55:00",
    "direction": "BUY",
    "open": 4557.008,
    "high": 4570.499,
    "low": 4555.785,
    "close": 4564.305,
    "volume": 4159,
    "candle_data": {
      "body": "72.97 pips",
      "ekor_atas": "61.94 pips",
      "ekor_bawah": "12.23 pips"
    }
  },
  {
    "time": "2026-05-29 15:00:00",
    "direction": "BUY",
    "open": 4564.25,
    "high": 4578.581,
    "low": 4564.088,
    "close": 4578.416,
    "volume": 4130,
    "candle_data": {
      "body": "141.66 pips",
      "ekor_atas": "1.65 pips",
      "ekor_bawah": "1.62 pips"
    }
  },
  {
    "time": "2026-05-29 15:05:00",
    "direction": "BUY",
    "open": 4578.2,
    "high": 4589.856,
    "low": 4573.68,
    "close": 4587.817,
    "volume": 4204,
    "candle_data": {
      "body": "96.17 pips",
      "ekor_atas": "20.39 pips",
      "ekor_bawah": "45.2 pips"
    }
  },
  {
    "time": "2026-05-29 15:10:00",
    "direction": "BUY",
    "open": 4587.756,
    "high": 4595.203,
    "low": 4585.744,
    "close": 4589.712,
    "volume": 3530,
    "candle_data": {
      "body": "19.56 pips",
      "ekor_atas": "54.91 pips",
      "ekor_bawah": "20.12 pips"
    }
  },
  {
    "time": "2026-05-29 15:15:00",
    "direction": "SELL",
    "open": 4589.767,
    "high": 4591.537,
    "low": 4585.805,
    "close": 4588.443,
    "volume": 2652,
    "candle_data": {
      "body": "13.24 pips",
      "ekor_atas": "17.7 pips",
      "ekor_bawah": "26.38 pips"
    }
  },
  {
    "time": "2026-05-29 15:20:00",
    "direction": "SELL",
    "open": 4588.501,
    "high": 4589.126,
    "low": 4581.635,
    "close": 4584.709,
    "volume": 2346,
    "candle_data": {
      "body": "37.92 pips",
      "ekor_atas": "6.25 pips",
      "ekor_bawah": "30.74 pips"
    }
  },
  {
    "time": "2026-05-29 15:25:00",
    "direction": "SELL",
    "open": 4584.654,
    "high": 4585.374,
    "low": 4577.876,
    "close": 4578.22,
    "volume": 1725,
    "candle_data": {
      "body": "64.34 pips",
      "ekor_atas": "7.2 pips",
      "ekor_bawah": "3.44 pips"
    }
  },
  {
    "time": "2026-05-29 15:30:00",
    "direction": "SELL",
    "open": 4578.302,
    "high": 4583.363,
    "low": 4577.733,
    "close": 4578.172,
    "volume": 1679,
    "candle_data": {
      "body": "1.3 pips",
      "ekor_atas": "50.61 pips",
      "ekor_bawah": "4.39 pips"
    }
  },
  {
    "time": "2026-05-29 15:35:00",
    "direction": "SELL",
    "open": 4578.374,
    "high": 4580.808,
    "low": 4571.97,
    "close": 4573.094,
    "volume": 2258,
    "candle_data": {
      "body": "52.8 pips",
      "ekor_atas": "24.34 pips",
      "ekor_bawah": "11.24 pips"
    }
  },
  {
    "time": "2026-05-29 15:40:00",
    "direction": "SELL",
    "open": 4573.188,
    "high": 4575.336,
    "low": 4561.263,
    "close": 4566.393,
    "volume": 3196,
    "candle_data": {
      "body": "67.95 pips",
      "ekor_atas": "21.48 pips",
      "ekor_bawah": "51.3 pips"
    }
  },
  {
    "time": "2026-05-29 15:45:00",
    "direction": "SELL",
    "open": 4566.472,
    "high": 4569.369,
    "low": 4557.679,
    "close": 4565.039,
    "volume": 2510,
    "candle_data": {
      "body": "14.33 pips",
      "ekor_atas": "28.97 pips",
      "ekor_bawah": "73.6 pips"
    }
  },
  {
    "time": "2026-05-29 15:50:00",
    "direction": "BUY",
    "open": 4564.905,
    "high": 4570.517,
    "low": 4563.288,
    "close": 4569.132,
    "volume": 1416,
    "candle_data": {
      "body": "42.27 pips",
      "ekor_atas": "13.85 pips",
      "ekor_bawah": "16.17 pips"
    }
  },
  {
    "time": "2026-05-29 15:55:00",
    "direction": "BUY",
    "open": 4568.832,
    "high": 4571.597,
    "low": 4568.161,
    "close": 4571.217,
    "volume": 1192,
    "candle_data": {
      "body": "23.85 pips",
      "ekor_atas": "3.8 pips",
      "ekor_bawah": "6.71 pips"
    }
  },
  {
    "time": "2026-05-29 16:00:00",
    "direction": "SELL",
    "open": 4571.282,
    "high": 4572.327,
    "low": 4567.628,
    "close": 4568.032,
    "volume": 1286,
    "candle_data": {
      "body": "32.5 pips",
      "ekor_atas": "10.45 pips",
      "ekor_bawah": "4.04 pips"
    }
  },
  {
    "time": "2026-05-29 16:05:00",
    "direction": "SELL",
    "open": 4567.887,
    "high": 4569.043,
    "low": 4563.647,
    "close": 4564.35,
    "volume": 1013,
    "candle_data": {
      "body": "35.37 pips",
      "ekor_atas": "11.56 pips",
      "ekor_bawah": "7.03 pips"
    }
  },
  {
    "time": "2026-05-29 16:10:00",
    "direction": "SELL",
    "open": 4564.322,
    "high": 4565.12,
    "low": 4559.655,
    "close": 4563.767,
    "volume": 917,
    "candle_data": {
      "body": "5.55 pips",
      "ekor_atas": "7.98 pips",
      "ekor_bawah": "41.12 pips"
    }
  },
  {
    "time": "2026-05-29 16:15:00",
    "direction": "BUY",
    "open": 4563.704,
    "high": 4567.778,
    "low": 4562.758,
    "close": 4565.339,
    "volume": 910,
    "candle_data": {
      "body": "16.35 pips",
      "ekor_atas": "24.39 pips",
      "ekor_bawah": "9.46 pips"
    }
  },
  {
    "time": "2026-05-29 16:20:00",
    "direction": "SELL",
    "open": 4565.107,
    "high": 4567.143,
    "low": 4563.651,
    "close": 4564.389,
    "volume": 883,
    "candle_data": {
      "body": "7.18 pips",
      "ekor_atas": "20.36 pips",
      "ekor_bawah": "7.38 pips"
    }
  },
  {
    "time": "2026-05-29 16:25:00",
    "direction": "SELL",
    "open": 4564.327,
    "high": 4564.327,
    "low": 4560.434,
    "close": 4563.138,
    "volume": 999,
    "candle_data": {
      "body": "11.89 pips",
      "ekor_atas": "0.0 pips",
      "ekor_bawah": "27.04 pips"
    }
  },
  {
    "time": "2026-05-29 16:30:00",
    "direction": "BUY",
    "open": 4563.063,
    "high": 4570.113,
    "low": 4561.745,
    "close": 4569.03,
    "volume": 1668,
    "candle_data": {
      "body": "59.67 pips",
      "ekor_atas": "10.83 pips",
      "ekor_bawah": "13.18 pips"
    }
  },
  {
    "time": "2026-05-29 16:35:00",
    "direction": "BUY",
    "open": 4569.09,
    "high": 4573.474,
    "low": 4567.522,
    "close": 4571.909,
    "volume": 1163,
    "candle_data": {
      "body": "28.19 pips",
      "ekor_atas": "15.65 pips",
      "ekor_bawah": "15.68 pips"
    }
  },
  {
    "time": "2026-05-29 16:40:00",
    "direction": "SELL",
    "open": 4571.909,
    "high": 4572.841,
    "low": 4568.385,
    "close": 4569.298,
    "volume": 935,
    "candle_data": {
      "body": "26.11 pips",
      "ekor_atas": "9.32 pips",
      "ekor_bawah": "9.13 pips"
    }
  },
  {
    "time": "2026-05-29 16:45:00",
    "direction": "SELL",
    "open": 4569.602,
    "high": 4569.602,
    "low": 4564.359,
    "close": 4564.654,
    "volume": 941,
    "candle_data": {
      "body": "49.48 pips",
      "ekor_atas": "0.0 pips",
      "ekor_bawah": "2.95 pips"
    }
  },
  {
    "time": "2026-05-29 16:50:00",
    "direction": "BUY",
    "open": 4564.692,
    "high": 4565.912,
    "low": 4560.845,
    "close": 4565.479,
    "volume": 828,
    "candle_data": {
      "body": "7.87 pips",
      "ekor_atas": "4.33 pips",
      "ekor_bawah": "38.47 pips"
    }
  },
  {
    "time": "2026-05-29 16:55:00",
    "direction": "BUY",
    "open": 4565.122,
    "high": 4567.328,
    "low": 4562.436,
    "close": 4566.776,
    "volume": 593,
    "candle_data": {
      "body": "16.54 pips",
      "ekor_atas": "5.52 pips",
      "ekor_bawah": "26.86 pips"
    }
  },
  {
    "time": "2026-05-29 17:00:00",
    "direction": "SELL",
    "open": 4566.836,
    "high": 4568.126,
    "low": 4564.189,
    "close": 4564.315,
    "volume": 652,
    "candle_data": {
      "body": "25.21 pips",
      "ekor_atas": "12.9 pips",
      "ekor_bawah": "1.26 pips"
    }
  },
  {
    "time": "2026-05-29 17:05:00",
    "direction": "BUY",
    "open": 4564.382,
    "high": 4568.637,
    "low": 4563.265,
    "close": 4567.322,
    "volume": 564,
    "candle_data": {
      "body": "29.4 pips",
      "ekor_atas": "13.15 pips",
      "ekor_bawah": "11.17 pips"
    }
  },
  {
    "time": "2026-05-29 17:10:00",
    "direction": "SELL",
    "open": 4567.537,
    "high": 4568.232,
    "low": 4563.826,
    "close": 4564.214,
    "volume": 642,
    "candle_data": {
      "body": "33.23 pips",
      "ekor_atas": "6.95 pips",
      "ekor_bawah": "3.88 pips"
    }
  },
  {
    "time": "2026-05-29 17:15:00",
    "direction": "BUY",
    "open": 4564.202,
    "high": 4566.79,
    "low": 4563.645,
    "close": 4565.687,
    "volume": 625,
    "candle_data": {
      "body": "14.85 pips",
      "ekor_atas": "11.03 pips",
      "ekor_bawah": "5.57 pips"
    }
  },
  {
    "time": "2026-05-29 17:20:00",
    "direction": "SELL",
    "open": 4565.665,
    "high": 4566.867,
    "low": 4560.715,
    "close": 4565.357,
    "volume": 976,
    "candle_data": {
      "body": "3.08 pips",
      "ekor_atas": "12.02 pips",
      "ekor_bawah": "46.42 pips"
    }
  },
  {
    "time": "2026-05-29 17:25:00",
    "direction": "SELL",
    "open": 4565.415,
    "high": 4565.947,
    "low": 4561.641,
    "close": 4561.952,
    "volume": 881,
    "candle_data": {
      "body": "34.63 pips",
      "ekor_atas": "5.32 pips",
      "ekor_bawah": "3.11 pips"
    }
  },
  {
    "time": "2026-05-29 17:30:00",
    "direction": "SELL",
    "open": 4561.884,
    "high": 4562.301,
    "low": 4557.756,
    "close": 4559.063,
    "volume": 551,
    "candle_data": {
      "body": "28.21 pips",
      "ekor_atas": "4.17 pips",
      "ekor_bawah": "13.07 pips"
    }
  }
]
